git_ignores/__init__.py
git_ignores/console.py
git_ignores/helpers.py
git_ignores-0.1.1.dist-info/entry_points.txt
git_ignores-0.1.1.dist-info/WHEEL
git_ignores-0.1.1.dist-info/METADATA
git_ignores-0.1.1.dist-info/RECORD
